fx_lib/__init__.py
fx_lib/config.py
fx_lib/datetime_ext.py
fx_lib/func.py
fx_lib/fx_lib.py
fx_lib/list_ext.py
fx_lib/log.py
fx_lib/math.py
fx_lib/str_ext.py
fx_lib/zoho_email.py
fx_lib-0.5.3.dist-info/licenses/LICENSE
fx_lib-0.5.3.dist-info/METADATA
fx_lib-0.5.3.dist-info/WHEEL
fx_lib-0.5.3.dist-info/top_level.txt
fx_lib-0.5.3.dist-info/RECORD
